runes/__init__.py
runes/runes.py
runes-0.5.dist-info/METADATA
runes-0.5.dist-info/WHEEL
runes-0.5.dist-info/top_level.txt
runes-0.5.dist-info/zip-safe
runes-0.5.dist-info/RECORD
