Metadata-Version: 2.1
Name: runes
Version: 0.5
Summary: Simple Cookies You Can Extend (similar to Macaroons)
Home-page: http://github.com/rustyrussell/runes
Author: Rusty Russell
Author-email: rusty@rustcorp.com.au
License: MIT
Platform: UNKNOWN
Requires-Dist: sha256
